molalchemy/__init__.py
molalchemy/_version.py
molalchemy/alembic_helpers.py
molalchemy/base.py
molalchemy/helpers.py
molalchemy/py.typed
molalchemy/types.py
molalchemy/bingo/__init__.py
molalchemy/bingo/comparators.py
molalchemy/bingo/index.py
molalchemy/bingo/proxy.py
molalchemy/bingo/types.py
molalchemy/bingo/functions/__init__.py
molalchemy/bingo/functions/general.py
molalchemy/bingo/functions/internal.py
molalchemy/rdkit/__init__.py
molalchemy/rdkit/comparators.py
molalchemy/rdkit/index.py
molalchemy/rdkit/types.py
molalchemy/rdkit/functions/__init__.py
molalchemy/rdkit/functions/general.py
molalchemy/rdkit/functions/internal.py
molalchemy-0.0.5.dist-info/METADATA
molalchemy-0.0.5.dist-info/WHEEL
molalchemy-0.0.5.dist-info/licenses/LICENSE
molalchemy-0.0.5.dist-info/RECORD
