Metadata-Version: 2.4
Name: molalchemy
Version: 0.0.5
Summary: Extensions for SQLAlchemy to work with chemical cartridges
Project-URL: homepage, https://github.com/asiomchen/molalchemy
Project-URL: repository, https://github.com/asiomchen/molalchemy
Project-URL: documentation, https://molalchemy.readthedocs.io
Author-email: Anton Siomchen <anton.siomchen+molalchemy@gmail.com>
License:                                 Apache License
License-File: LICENSE
Keywords: cheminformatics,chemistry,databases,molecules,reactions
Classifier: Development Status :: 3 - Alpha
Classifier: Intended Audience :: Science/Research
Classifier: License :: OSI Approved :: Apache Software License
Classifier: Programming Language :: Python :: 3 :: Only
Classifier: Programming Language :: Python :: 3.10
Classifier: Programming Language :: Python :: 3.11
Classifier: Programming Language :: Python :: 3.12
Classifier: Programming Language :: Python :: 3.13
Classifier: Topic :: Database
Classifier: Topic :: Scientific/Engineering
Classifier: Topic :: Utilities
Requires-Python: <3.15,>=3.10
Requires-Dist: loguru>=0.7.0
Requires-Dist: psycopg>=3.0.0
Requires-Dist: rdkit>=2024.3.1
Requires-Dist: sqlalchemy>=2.0.0
